[{"name":"ds_user_id","value":"23880529662","domain":".instagram.com","path":"/","expires":1733750328.353817,"size":21,"httpOnly":false,"secure":true,"session":false,"priority":"Medium","sameParty":false,"sourceScheme":"Secure"},{"name":"rur","value":"\"LDC\\05423880529662\\0541757510328:01f7a2c13a979ba49578a80bdb31b48f922ae5f09adc596c389faf01e9c204550ce85b30\"","domain":".instagram.com","path":"/","expires":-1,"size":110,"httpOnly":true,"secure":true,"session":true,"sameSite":"Lax","priority":"Medium","sameParty":false,"sourceScheme":"Secure"},{"name":"csrftoken","value":"69eBs0hZGV6yv9RhYiH89tcJXf3C6fQK","domain":".instagram.com","path":"/","expires":1757423928.353541,"size":41,"httpOnly":false,"secure":true,"session":false,"priority":"Medium","sameParty":false,"sourceScheme":"Secure"},{"name":"ig_did","value":"543490BF-7FC4-4E50-8555-95C41D5C5CAF","domain":".instagram.com","path":"/","expires":1757510328.35402,"size":42,"httpOnly":true,"secure":true,"session":false,"priority":"Medium","sameParty":false,"sourceScheme":"Secure"},{"name":"datr","value":"KEfgZnHkyLX-bxFwqwty1t3E","domain":".instagram.com","path":"/","expires":1760534314.234575,"size":28,"httpOnly":true,"secure":true,"session":false,"sameSite":"None","priority":"Medium","sameParty":false,"sourceScheme":"Secure"},{"name":"wd","value":"1440x758","domain":".instagram.com","path":"/","expires":1726579131,"size":10,"httpOnly":false,"secure":true,"session":false,"sameSite":"Lax","priority":"Medium","sameParty":false,"sourceScheme":"Secure"},{"name":"mid","value":"ZuBHKAAEAAGH4DLk2IfemJ9SwLuX","domain":".instagram.com","path":"/","expires":1760534313,"size":31,"httpOnly":false,"secure":true,"session":false,"priority":"Medium","sameParty":false,"sourceScheme":"Secure"},{"name":"sessionid","value":"23880529662%3At04WJQHwfMliwg%3A23%3AAYefljyAdchpsmxlBjgI3QnACnbFOm8SvVclerV-rg","domain":".instagram.com","path":"/","expires":1757510328.354111,"size":87,"httpOnly":true,"secure":true,"session":false,"priority":"Medium","sameParty":false,"sourceScheme":"Secure"},{"name":"dpr","value":"1","domain":".instagram.com","path":"/","expires":1726579131,"size":4,"httpOnly":false,"secure":true,"session":false,"sameSite":"None","priority":"Medium","sameParty":false,"sourceScheme":"Secure"}]